README
deploy
setup.py
deploy_class/__init__.py
deploy_class/argparser.py
deploy_class/cvsystems.py
deploy_class/db.py
deploy_class/deployer.py
deploy_class/executors.py
deploy_class/globals.py
deploy_class/hook.py
deploy_class/projects.py
python_web_deployer.egg-info/PKG-INFO
python_web_deployer.egg-info/SOURCES.txt
python_web_deployer.egg-info/dependency_links.txt
python_web_deployer.egg-info/requires.txt
python_web_deployer.egg-info/top_level.txt