Metadata-Version: 1.1
Name: python-web-deployer
Version: 0.2.0
Summary: ('Deploy you sites to remote server',)
Home-page: sallyruthstruik.bitbucket.org/python-web-deployer
Author: Kaledin Stas
Author-email: staskaledin@gmail.com
License: BSD
Keywords: web deploy deployment
Platform: UNKNOWN
Classifier: Development Status :: 3 - Alpha
Classifier: License :: OSI Approved :: BSD License
